twcrawl/__init__.py
twcrawl/cli.py
twcrawl/crawler.py
twcrawl/models.py
twcrawl/twitter.py
twcrawl-1.0.1.dist-info/LICENSE
twcrawl-1.0.1.dist-info/METADATA
twcrawl-1.0.1.dist-info/WHEEL
twcrawl-1.0.1.dist-info/entry_points.txt
twcrawl-1.0.1.dist-info/top_level.txt
twcrawl-1.0.1.dist-info/RECORD
