Metadata-Version: 2.1
Name: twcrawl
Version: 1.0.1
Summary: Twitter crawler to download a followers graph and statuses into a local database.
Home-page: https://github.com/hohl/twcrawl
Author: Michael Hohl
Author-email: me@michaelhohl.net
License: UNKNOWN
Platform: UNKNOWN
Classifier: Programming Language :: Python :: 3
Classifier: License :: OSI Approved :: MIT License
Classifier: Operating System :: OS Independent
Requires-Python: >=3.6
Requires-Dist: twitter
Requires-Dist: tweepy
Requires-Dist: sqlalchemy
